tconnectsync/__init__.py
tconnectsync/__main__.py
tconnectsync/check.py
tconnectsync/features.py
tconnectsync/nightscout.py
tconnectsync/process.py
tconnectsync/secret.py
tconnectsync/api/__init__.py
tconnectsync/api/android.py
tconnectsync/api/common.py
tconnectsync/api/controliq.py
tconnectsync/api/tandemsource.py
tconnectsync/api/webui.py
tconnectsync/api/ws2.py
tconnectsync/domain/__init__.py
tconnectsync/domain/bolus.py
tconnectsync/domain/device_settings.py
tconnectsync/domain/therapy_event.py
tconnectsync/domain/utility.py
tconnectsync/domain/tandemsource/__init__.py
tconnectsync/domain/tandemsource/event_class.py
tconnectsync/domain/tandemsource/pump_settings.py
tconnectsync/eventparser/__init__.py
tconnectsync/eventparser/build_events.py
tconnectsync/eventparser/events.py
tconnectsync/eventparser/generic.py
tconnectsync/eventparser/raw_event.py
tconnectsync/eventparser/static_dicts.py
tconnectsync/eventparser/transforms.py
tconnectsync/eventparser/utils.py
tconnectsync/parser/__init__.py
tconnectsync/parser/ciq_therapy_events.py
tconnectsync/parser/nightscout.py
tconnectsync/parser/tconnect.py
tconnectsync/sync/__init__.py
tconnectsync/sync/tandemsource/__init__.py
tconnectsync/sync/tandemsource/autoupdate.py
tconnectsync/sync/tandemsource/choose_device.py
tconnectsync/sync/tandemsource/cli_helpers.py
tconnectsync/sync/tandemsource/helpers.py
tconnectsync/sync/tandemsource/heroku_helpers.py
tconnectsync/sync/tandemsource/process.py
tconnectsync/sync/tandemsource/process_alarm.py
tconnectsync/sync/tandemsource/process_basal.py
tconnectsync/sync/tandemsource/process_basal_resume.py
tconnectsync/sync/tandemsource/process_basal_suspension.py
tconnectsync/sync/tandemsource/process_bolus.py
tconnectsync/sync/tandemsource/process_cartridge.py
tconnectsync/sync/tandemsource/process_cgm_alert.py
tconnectsync/sync/tandemsource/process_cgm_reading.py
tconnectsync/sync/tandemsource/process_cgm_start_join_stop.py
tconnectsync/sync/tandemsource/process_device_status.py
tconnectsync-2.3.4.dist-info/licenses/LICENSE.md
tconnectsync-2.3.4.dist-info/METADATA
tconnectsync-2.3.4.dist-info/WHEEL
tconnectsync-2.3.4.dist-info/entry_points.txt
tconnectsync-2.3.4.dist-info/top_level.txt
tconnectsync-2.3.4.dist-info/RECORD
