Metadata-Version: 2.4
Name: tconnectsync
Version: 2.3.4
Summary: Syncs Tandem Source (formerly t:connect) insulin pump data to Nightscout for the t:slim X2
Home-page: https://github.com/jwoglom/tconnectsync
Author: James Woglom
Author-email: j@wogloms.net
Project-URL: Bug Tracker, https://github.com/jwoglom/tconnectsync/issues
Classifier: Programming Language :: Python :: 3
Classifier: License :: OSI Approved :: MIT License
Classifier: Operating System :: OS Independent
Requires-Python: >=3.7
License-File: LICENSE.md
Requires-Dist: requests
Requires-Dist: bs4
Requires-Dist: arrow
Requires-Dist: lxml
Requires-Dist: python-dotenv
Requires-Dist: requests-mock
Requires-Dist: pysocks
Requires-Dist: urllib3
Requires-Dist: requests
Requires-Dist: requests-oidc
Requires-Dist: PyJWT
Requires-Dist: cryptography
Requires-Dist: dataclasses-json
Requires-Dist: cffi
Requires-Dist: typing-extensions
Dynamic: license-file
